{
  "courseId": 21,
  "instructorId": 2,
  "title": "Web Technologies",
  "description": "learn web tech",
  "price": 30,
  "numberOfLectures": 3,
  "lectures": [
    {
      "lectureNumber": 1,
      "title": "lecture 1",
      "video": {
        "originalName": "siimipie_1764939282_3780906920304632416_69770313028.mp4",
        "mimeType": "video/mp4",
        "storagePath": "/uploads/videos/1765137771794-501042632.mp4",
        "filename": "1765137771794-501042632.mp4",
        "size": 1604718
      },
      "materials": [
        {
          "originalName": "screenshot-2025-11-29_23-27-22.png",
          "mimeType": "image/png",
          "storagePath": "/uploads/materials/1765137771800-890363769.png",
          "filename": "1765137771800-890363769.png"
        }
      ]
    },
    {
      "lectureNumber": 2,
      "title": "lecture 2",
      "video": {
        "originalName": "siimipie_1764936119_3780880122560824404_69770313028.mp4",
        "mimeType": "video/mp4",
        "storagePath": "/uploads/videos/1765137771801-26715207.mp4",
        "filename": "1765137771801-26715207.mp4",
        "size": 3243337
      },
      "materials": [
        {
          "originalName": "screenshot-2025-11-18_17-13-27.png",
          "mimeType": "image/png",
          "storagePath": "/uploads/materials/1765137771809-560181429.png",
          "filename": "1765137771809-560181429.png"
        }
      ]
    },
    {
      "lectureNumber": 3,
      "title": "lecture 3",
      "video": {
        "originalName": "siimipie_1764939282_3780906920304632416_69770313028.mp4",
        "mimeType": "video/mp4",
        "storagePath": "/uploads/videos/1765137771810-515444045.mp4",
        "filename": "1765137771810-515444045.mp4",
        "size": 1604718
      },
      "materials": [
        {
          "originalName": "screenshot-2025-11-29_23-16-07.png",
          "mimeType": "image/png",
          "storagePath": "/uploads/materials/1765137771814-346755186.png",
          "filename": "1765137771814-346755186.png"
        },
        {
          "originalName": "screenshot-2025-11-29_23-16-32.png",
          "mimeType": "image/png",
          "storagePath": "/uploads/materials/1765137771814-349755706.png",
          "filename": "1765137771814-349755706.png"
        }
      ]
    }
  ],
  "createdAt": "2025-12-07T20:02:51.833Z"
}